README.rst
setup.py
testit.py
src/__init__.py
src/api.py
src/json_fixture.py
src/listener.py
src/plugin.py
src/plugin_manager.py
src/utils.py
testit_pytest.egg-info/PKG-INFO
testit_pytest.egg-info/SOURCES.txt
testit_pytest.egg-info/dependency_links.txt
testit_pytest.egg-info/entry_points.txt
testit_pytest.egg-info/requires.txt
testit_pytest.egg-info/top_level.txt